LICENSE
README.md
setup.cfg
setup.py
infoFunWP/__init__.py
infoFunWP/infoFun.py
infoFunWP.egg-info/PKG-INFO
infoFunWP.egg-info/SOURCES.txt
infoFunWP.egg-info/dependency_links.txt
infoFunWP.egg-info/top_level.txt