Metadata-Version: 2.1
Name: infoFunWP
Version: 0.1.1
Summary: Wrapper around built in IO functions for reading text files - for teaching purposes
Home-page: https://github.com/jverwaer/infoFun
Download-URL: https://github.com/jverwaer/infoFun
Author: Jan Verwaeren
Author-email: Jan.Verwaeren@UGent.be
License: GNU
Classifier: Development Status :: 4 - Beta
Classifier: Programming Language :: Python :: 3
Classifier: Programming Language :: Python :: 3 :: Only
Classifier: Programming Language :: Python :: 3.9
Classifier: License :: OSI Approved :: GNU General Public License (GPL)
Classifier: Intended Audience :: Science/Research
Classifier: Operating System :: Microsoft :: Windows
Classifier: Operating System :: Unix
Classifier: Operating System :: MacOS
License-File: LICENSE
